promptia/__init__.py
promptia/core/__init__.py
promptia/core/defines.py
promptia/core/manager.py
promptia/llm/__init__.py
promptia/llm/adapter.py
promptia/llm/azure.py
promptia/llm/bedrock.py
promptia/llm/openai.py
promptia/retrievers/__init__.py
promptia/retrievers/base.py
promptia/retrievers/vector_retriever.py
promptia/storages/__init__.py
promptia/storages/base.py
promptia/storages/file_storage.py
promptia/storages/memory_storage.py
promptia/storages/s3_storage.py
promptia-0.5.1.dist-info/LICENSE
promptia-0.5.1.dist-info/METADATA
promptia-0.5.1.dist-info/WHEEL
promptia-0.5.1.dist-info/RECORD
