Metadata-Version: 2.1
Name: promptia
Version: 0.5.1
Summary: Promptia is a Python library designed to streamline the management and generation of prompts for Large Language Models (LLMs).
Author: tamuto
Author-email: tamuto@infodb.jp
Requires-Python: >=3.10,<4.0
Classifier: Programming Language :: Python :: 3
Classifier: Programming Language :: Python :: 3.10
Classifier: Programming Language :: Python :: 3.11
Classifier: Programming Language :: Python :: 3.12
Provides-Extra: aws
Provides-Extra: local-index
Provides-Extra: openai
Requires-Dist: boto3 (>=1.35.20,<2.0.0) ; extra == "aws"
Requires-Dist: faiss-cpu (>=1.8.0.post1,<2.0.0) ; extra == "local-index"
Requires-Dist: jinja2 (>=3.1.4,<4.0.0)
Requires-Dist: openai (>=1.46.0,<2.0.0) ; extra == "openai"
Requires-Dist: pydantic (>=2.9.1,<3.0.0)
Requires-Dist: sentence-transformers (>=3.1.0,<4.0.0) ; extra == "local-index"
